CloudEdgeAssetsOptimizer/CloudEdgeAssetOptimizer.py
CloudEdgeAssetsOptimizer/__init__.py
CloudEdgeAssetsOptimizer/calculation.py
CloudEdgeAssetsOptimizer/graph.py
CloudEdgeAssetsOptimizer/gui_frontend.py
CloudEdgeAssetsOptimizer/optimizer.py
CloudEdgeAssetsOptimizer/qsystems.py
CloudEdgeAssetsOptimizer-0.1.4.dist-info/LICENSE
CloudEdgeAssetsOptimizer-0.1.4.dist-info/METADATA
CloudEdgeAssetsOptimizer-0.1.4.dist-info/WHEEL
CloudEdgeAssetsOptimizer-0.1.4.dist-info/entry_points.txt
CloudEdgeAssetsOptimizer-0.1.4.dist-info/top_level.txt
CloudEdgeAssetsOptimizer-0.1.4.dist-info/RECORD
