Metadata-Version: 2.1
Name: CloudEdgeAssetsOptimizer
Version: 0.1.4
Summary: # CloudEdgeAssetsOptimizer   
Home-page: https://github.com/pauterv/CloudEdgeAssetsOptimizer
Author: Paulius Tervydis
Author-email: Paulius.Tervydis@ktu.lt
Classifier: Development Status :: 3 - Alpha
Classifier: License :: OSI Approved :: MIT License
Classifier: Programming Language :: Python :: 3
Classifier: Programming Language :: Python :: 3.6
Classifier: Programming Language :: Python :: 3.7
Classifier: Programming Language :: Python :: 3.8
License-File: LICENSE
Requires-Dist: numpy
Requires-Dist: pandas
Requires-Dist: matplotlib
Requires-Dist: Pillow
